{"is_source_file": true, "format": "JavaScript", "description": "React component ResultsPage that fetches and displays quiz results after submission, including score, answers review, and navigation back to the quiz list.", "external_files": ["../utils/api", "react", "react-router-dom"], "external_methods": ["api.quizzes.getResult", "useParams", "useNavigate"], "published": ["ResultsPage"], "classes": [], "methods": [{"name": "ResultsPage()", "description": "React functional component to display quiz results, including loading, error handling, and review details.", "scope": "", "scopeKind": ""}], "calls": ["api.quizzes.getResult", "useParams", "useNavigate", "setResult", "setLoading", "setError", "navigate"], "search-terms": ["ResultsPage", "quiz results display", "React quiz review", "useParams", "useNavigate", "getResult"], "state": 2, "file_id": 13, "knowledge_revision": 33, "git_revision": "48882208801f9f6e77ddfecce4fc445bba7c5177", "ctags": [{"_type": "tag", "name": "ResultsPage", "path": "/home/kavia/workspace/code-generation/online-quiz-platform-304472-304481/quiz_frontend/src/components/ResultsPage.js", "pattern": "/^function ResultsPage() {$/", "language": "JavaScript", "kind": "function", "signature": "()"}], "hash": "0b5e7fdde30c904fbe325581aec86648", "format-version": 4, "code-base-name": "quiz_frontend", "filename": "quiz_frontend/src/components/ResultsPage.js", "revision_history": [{"33": "48882208801f9f6e77ddfecce4fc445bba7c5177"}]}